airtm/__init__.py
airtm/__main__.py
airtm/airtm.py
airtm/cli.py
airtm/gui.py
airtm-0.1.1.dist-info/LICENSE.md
airtm-0.1.1.dist-info/METADATA
airtm-0.1.1.dist-info/WHEEL
airtm-0.1.1.dist-info/top_level.txt
airtm-0.1.1.dist-info/RECORD
