Metadata-Version: 2.1
Name: airtm
Version: 0.1.1
Summary: Library for AirTM's API
Home-page: https://bitbucket.org/airtm/payments-sdk-python
Author: AirTM
Author-email: partners@airtm.io
License: UNKNOWN
Keywords: airtm,api
Platform: UNKNOWN
Requires-Dist: urllib3
Requires-Dist: requests
Requires-Dist: configparser
Requires-Dist: pprint
